debugaa1/__init__.py
debugaa1/hello_world_method.py
debugaa1/printing_methods.py
debugaa1-0.1.1.dist-info/LICENSE.txt
debugaa1-0.1.1.dist-info/METADATA
debugaa1-0.1.1.dist-info/WHEEL
debugaa1-0.1.1.dist-info/top_level.txt
debugaa1-0.1.1.dist-info/RECORD
